stock_pairs_trading/__init__.py
stock_pairs_trading/stock_pairs_trading.py
stock_pairs_trading-0.1.1.dist-info/LICENSE.txt
stock_pairs_trading-0.1.1.dist-info/METADATA
stock_pairs_trading-0.1.1.dist-info/WHEEL
stock_pairs_trading-0.1.1.dist-info/top_level.txt
stock_pairs_trading-0.1.1.dist-info/RECORD
