Metadata-Version: 2.1
Name: stock-pairs-trading
Version: 0.1.1
Summary: stock-pairs-trading is a python library         for backtest with stock pairs trading using kalman filter on Python 3.8 and above.
Home-page: https://github.com/10mohi6/stock-pairs-trading-python
Author: 10mohi6
Author-email: 10.mohi.6.y@gmail.com
License: MIT
Keywords: pairs trading python backtest stock kalman filter
Classifier: Development Status :: 4 - Beta
Classifier: Programming Language :: Python
Classifier: Programming Language :: Python :: 3
Classifier: Programming Language :: Python :: 3.8
Classifier: Programming Language :: Python :: 3.9
Classifier: Intended Audience :: Developers
Classifier: Intended Audience :: Financial and Insurance Industry
Classifier: Operating System :: OS Independent
Classifier: Topic :: Office/Business :: Financial :: Investment
Classifier: License :: OSI Approved :: MIT License
Requires-Python: >=3.8.0
License-File: LICENSE.txt
Requires-Dist: yfinance
Requires-Dist: matplotlib
Requires-Dist: statsmodels
Requires-Dist: pykalman
Requires-Dist: seaborn
